Xv6ZhongwenWendang/README.md
Xv6ZhongwenWendang/__init__.py
Xv6ZhongwenWendang/__main__.py
Xv6ZhongwenWendang/file.epub
Xv6ZhongwenWendang/index.html
Xv6ZhongwenWendang/css/__init__.py
Xv6ZhongwenWendang/css/annotations.css
Xv6ZhongwenWendang/css/main.css
Xv6ZhongwenWendang/css/normalize.css
Xv6ZhongwenWendang/css/popup.css
Xv6ZhongwenWendang/font/__init__.py
Xv6ZhongwenWendang/font/fontello.eot
Xv6ZhongwenWendang/font/fontello.svg
Xv6ZhongwenWendang/font/fontello.ttf
Xv6ZhongwenWendang/font/fontello.woff
Xv6ZhongwenWendang/img/__init__.py
Xv6ZhongwenWendang/img/annotator-glyph-sprite.png
Xv6ZhongwenWendang/img/annotator-icon-sprite.png
Xv6ZhongwenWendang/img/apple-touch-icon.png
Xv6ZhongwenWendang/img/cancelfullscreen.png
Xv6ZhongwenWendang/img/close.png
Xv6ZhongwenWendang/img/fullscreen.png
Xv6ZhongwenWendang/img/loader.gif
Xv6ZhongwenWendang/img/menu-icon.png
Xv6ZhongwenWendang/img/save.png
Xv6ZhongwenWendang/img/saved.png
Xv6ZhongwenWendang/img/settings-s.png
Xv6ZhongwenWendang/img/settings.png
Xv6ZhongwenWendang/img/star.png
Xv6ZhongwenWendang/js/__init__.py
Xv6ZhongwenWendang/js/epub.js
Xv6ZhongwenWendang/js/epub.min.js
Xv6ZhongwenWendang/js/epub.min.map
Xv6ZhongwenWendang/js/hooks.min.js
Xv6ZhongwenWendang/js/hooks.min.map
Xv6ZhongwenWendang/js/reader.js
Xv6ZhongwenWendang/js/reader.js.map
Xv6ZhongwenWendang/js/reader.min.js
Xv6ZhongwenWendang/js/reader.min.map
Xv6ZhongwenWendang/js/hooks/__init__.py
Xv6ZhongwenWendang/js/hooks/extensions/__init__.py
Xv6ZhongwenWendang/js/hooks/extensions/highlight.js
Xv6ZhongwenWendang/js/libs/__init__.py
Xv6ZhongwenWendang/js/libs/jquery.min.js
Xv6ZhongwenWendang/js/libs/localforage.min.js
Xv6ZhongwenWendang/js/libs/screenfull.js
Xv6ZhongwenWendang/js/libs/screenfull.min.js
Xv6ZhongwenWendang/js/libs/zip.min.js
Xv6ZhongwenWendang/js/plugins/__init__.py
Xv6ZhongwenWendang/js/plugins/hypothesis.js
Xv6ZhongwenWendang/js/plugins/search.js
xv6_zhongwen_wendang-2024.3.2.0.dist-info/METADATA
xv6_zhongwen_wendang-2024.3.2.0.dist-info/WHEEL
xv6_zhongwen_wendang-2024.3.2.0.dist-info/entry_points.txt
xv6_zhongwen_wendang-2024.3.2.0.dist-info/top_level.txt
xv6_zhongwen_wendang-2024.3.2.0.dist-info/RECORD
